my_package/__init__.py
my_package/modul1.py
my_package/modul2.py
demo_project_2025_02_07-0.0.1.dist-info/METADATA
demo_project_2025_02_07-0.0.1.dist-info/WHEEL
demo_project_2025_02_07-0.0.1.dist-info/top_level.txt
demo_project_2025_02_07-0.0.1.dist-info/RECORD
